autodistill_vit/__init__.py
autodistill_vit/vit.py
autodistill_vit-0.1.0.dist-info/LICENSE
autodistill_vit-0.1.0.dist-info/METADATA
autodistill_vit-0.1.0.dist-info/WHEEL
autodistill_vit-0.1.0.dist-info/top_level.txt
autodistill_vit-0.1.0.dist-info/RECORD
